core/__init__.py
core/bootstrap.py
core/cli.py
core/elf.py
core/memory/__init__.py
core/memory/memory.py
core/tools/__init__.py
core/tools/base_subprocess.py
core/tools/fetch_page.py
core/tools/install_project.py
core/tools/rag_crawler.py
core/tools/run_python.py
core/tools/run_shell.py
core/tools/tool.py
core/tools/voice.py
core/tools/web_search.py
core/tools/recon/__init__.py
core/tools/recon/google_hacks.py
core/tools/recon/whois.py
judais/__init__.py
judais/judais.py
judais_lobi-0.6.4.dist-info/licenses/LICENSE
lobi/__init__.py
lobi/lobi.py
judais_lobi-0.6.4.dist-info/METADATA
judais_lobi-0.6.4.dist-info/WHEEL
judais_lobi-0.6.4.dist-info/entry_points.txt
judais_lobi-0.6.4.dist-info/top_level.txt
judais_lobi-0.6.4.dist-info/RECORD
