Metadata-Version: 2.4
Name: judais-lobi
Version: 0.6.4
Summary: JudAIs & Lobi: Dual-agent terminal AI with memory, automation, and attitude
Home-page: https://github.com/ginkorea/judais-lobi
Author: Josh Gompert
Classifier: Programming Language :: Python :: 3
Classifier: Environment :: Console
Classifier: License :: OSI Approved :: GNU General Public License v3 (GPLv3)
Classifier: Operating System :: OS Independent
Requires-Python: >=3.10
License-File: LICENSE
Requires-Dist: openai>=1.0.0
Requires-Dist: rich>=14.0.0
Requires-Dist: python-dotenv>=1.1.0
Requires-Dist: beautifulsoup4>=4.13.4
Requires-Dist: requests>=2.32.3
Requires-Dist: faiss-cpu>=1.11.0
Requires-Dist: numpy>=1.26.4
Requires-Dist: httpx>=0.28.1
Requires-Dist: httpcore>=1.0.9
Requires-Dist: h11>=0.16.0
Requires-Dist: sniffio>=1.3.1
Requires-Dist: pydantic>=2.11.0
Requires-Dist: annotated-types>=0.7.0
Requires-Dist: certifi>=2025.8.3
Provides-Extra: voice
Requires-Dist: simpleaudio>=1.0.4; extra == "voice"
Requires-Dist: TTS>=0.22.0; extra == "voice"
Requires-Dist: torch>=2.7.0; extra == "voice"
Requires-Dist: torchaudio>=2.7.0; extra == "voice"
Requires-Dist: soundfile>=0.13.1; extra == "voice"
Requires-Dist: audioread>=3.0.1; extra == "voice"
Requires-Dist: soxr>=0.5.0.post1; extra == "voice"
Requires-Dist: transformers>=4.51.3; extra == "voice"
Requires-Dist: huggingface-hub>=0.31.1; extra == "voice"
Requires-Dist: tokenizers>=0.21.1; extra == "voice"
Requires-Dist: safetensors>=0.5.3; extra == "voice"
Requires-Dist: trainer>=0.0.36; extra == "voice"
Dynamic: author
Dynamic: classifier
Dynamic: description
Dynamic: description-content-type
Dynamic: home-page
Dynamic: license-file
Dynamic: provides-extra
Dynamic: requires-dist
Dynamic: requires-python
Dynamic: summary
